fractrade_hl_simple/__init__.py
fractrade_hl_simple/api.py
fractrade_hl_simple/exceptions.py
fractrade_hl_simple/hyperliquid.py
fractrade_hl_simple/models.py
fractrade_hl_simple-0.1.15.dist-info/LICENSE
fractrade_hl_simple-0.1.15.dist-info/METADATA
fractrade_hl_simple-0.1.15.dist-info/WHEEL
fractrade_hl_simple-0.1.15.dist-info/RECORD
