Metadata-Version: 2.3
Name: fractrade-hl-simple
Version: 0.1.15
Summary: A simple API wrapper for automated trading on Hyperliquid DEX with Python
License: MIT
Keywords: hyperliquid,trading,crypto,api,defi
Author: crjameson
Author-email: 93468664+crjameson@users.noreply.github.com
Requires-Python: >=3.12,<4.0
Classifier: Development Status :: 3 - Alpha
Classifier: Intended Audience :: Developers
Classifier: License :: OSI Approved :: MIT License
Classifier: Programming Language :: Python :: 3
Classifier: Programming Language :: Python :: 3.12
Classifier: Programming Language :: Python :: 3.13
Classifier: Programming Language :: Python :: 3.10
Classifier: Programming Language :: Python :: 3.11
Classifier: Programming Language :: Python :: 3.8
Classifier: Programming Language :: Python :: 3.9
Requires-Dist: dacite (>=1.9.1,<2.0.0)
Requires-Dist: hyperliquid-python-sdk (>=0.10.0)
Requires-Dist: python-dotenv (>=1.0.1,<2.0.0)
Requires-Dist: requests (>=2.32.3,<3.0.0)
Project-URL: Documentation, https://github.com/fractrade-xyz/fractrade-hl-simple
Project-URL: Homepage, https://fractrade.xyz
Project-URL: Repository, https://github.com/fractrade-xyz/fractrade-hl-simple
